MANIFEST.in
README.txt
setup.py
docs/COPYRIGHT.txt
docs/HISTORY.txt
docs/LICENSE.txt
src/cromlech/__init__.py
src/cromlech.session.egg-info/PKG-INFO
src/cromlech.session.egg-info/SOURCES.txt
src/cromlech.session.egg-info/dependency_links.txt
src/cromlech.session.egg-info/namespace_packages.txt
src/cromlech.session.egg-info/not-zip-safe
src/cromlech.session.egg-info/requires.txt
src/cromlech.session.egg-info/top_level.txt
src/cromlech/session/__init__.py
src/cromlech/session/components.py
src/cromlech/session/prototypes.py
src/cromlech/session/transactions.py
src/cromlech/session/tests/test_prototypes.txt