Metadata-Version: 2.1
Name: cromlech.session
Version: 0.1
Summary: Server-side session components for WSGI or Non-WSGI apps.
Home-page: https://github.com/Cromlech
Author: The Cromlech team
Author-email: dolmen@list.dolmen-project.org
License: ZPL
Keywords: Cromlech
Platform: UNKNOWN
Classifier: Programming Language :: Python
Provides-Extra: test
Provides-Extra: transaction
